apps/__init__.py
apps/app.py
scripts/__init__.py
utils/__init__.py
acme_dash_board_pkg_rioatmadja2018-0.1.1609230039.dist-info/METADATA
acme_dash_board_pkg_rioatmadja2018-0.1.1609230039.dist-info/WHEEL
acme_dash_board_pkg_rioatmadja2018-0.1.1609230039.dist-info/top_level.txt
acme_dash_board_pkg_rioatmadja2018-0.1.1609230039.dist-info/zip-safe
acme_dash_board_pkg_rioatmadja2018-0.1.1609230039.dist-info/RECORD
