Metadata-Version: 2.1
Name: acme-dash-board-pkg-rioatmadja2018
Version: 0.1.1609230039
Summary: Python wheel to display the data.
Home-page: UNKNOWN
Author: Rio Atmadja
Author-email: rioatmadja2018@gmail.com
License: UNKNOWN
Platform: UNKNOWN
Classifier: Programming Language :: Python :: 3
Classifier: Operating System :: OS Independent
Classifier: Intended Audience :: Developers
Requires-Python: >=3.7
Requires-Dist: dash
Requires-Dist: dash-bootstrap-components
